Workbook
Name aporte: Simulador!$D$17
Name patrimonio: Simulador!$D$20
Name qtt_anos: Simulador!$D$18
Name rendimento_carteira: Simulador!$D$13
Name sugestao_investimento: Simulador!$D$14
Name taxa_mensal: Simulador!$D$19

Sheet Simulador
B11: CONFIGURAÇÕES
B12: Salário | D12: 10000
B13: Rendimento de Carteira | D13: 0.006
B14: Sugestão de Investimento (30%) | D14: =D12*30% -> 3000
B16: INVESTIMENTO MENSAL
B17: Quanto investir por mês? | D17: 1500
B18: Por quantos anos? | D18: 5
B19: Taxa de rendimento mensal? | D19: 0.01079
B20: Patrimônio acumulado? | D20: =FV(taxa_mensal,qtt_anos*12,aporte*-1) -> 125665.37
B21: Dividendos mensais? | D21: =patrimonio*rendimento_carteira -> 753.99223
B23: CENÁRIOS | D23: DIVIDENDOS
A24: 2 | B24: Quanto em 2 anos? | C24: =FV($D$19,$A24*12,$D$17*-1) -> 40841.441 | D24: =C24*rendimento_carteira -> 245.04865
A25: 5 | B25: Quanto em 5 anos? | C25: =FV($D$19,$A25*12,$D$17*-1) -> 125665.37 | D25: =C25*rendimento_carteira -> 753.99223
A26: 10 | B26: Quanto em 10 anos? | C26: =FV($D$19,$A26*12,$D$17*-1) -> 364926.32 | D26: =C26*rendimento_carteira -> 2189.5579
A27: 20 | B27: Quanto em 20 anos? | C27: =FV($D$19,$A27*12,$D$17*-1) -> 1687797.6 | D27: =C27*rendimento_carteira -> 10126.786
A28: 30 | B28: Quanto em 30 anos? | C28: =FV($D$19,$A28*12,$D$17*-1) -> 6483254.5 | D28: =C28*rendimento_carteira -> 38899.527
B32: PERFIL | C32: Moderado
B33: VALOR A SER INVESTIDO POR MÊS | C33: =aporte -> 1500
B35: TIPO DE FII | C35: Percentual Sugerido | D35: Valores
B36: PAPEL | C36: =VLOOKUP($C$32&"-"&B36,Tabela_auxiliar!$B:$E,4,FALSE) -> 0.32 | D36: =C36*$C$33 -> 480
B37: TIJOLO | C37: =VLOOKUP($C$32&"-"&B37,Tabela_auxiliar!$B:$E,4,FALSE) -> 0.35 | D37: =C37*$C$33 -> 525
B38: HÍBRIDOS | C38: =VLOOKUP($C$32&"-"&B38,Tabela_auxiliar!$B:$E,4,FALSE) -> 0.08 | D38: =C38*$C$33 -> 120
B39: FOFs | C39: =VLOOKUP($C$32&"-"&B39,Tabela_auxiliar!$B:$E,4,FALSE) -> 0.05 | D39: =C39*$C$33 -> 75
B40: DESENVOLVIMENTO | C40: =VLOOKUP($C$32&"-"&B40,Tabela_auxiliar!$B:$E,4,FALSE) -> 0.1 | D40: =C40*$C$33 -> 150
B41: HOTELARIAS | C41: =VLOOKUP($C$32&"-"&B41,Tabela_auxiliar!$B:$E,4,FALSE) -> 0.1 | D41: =C41*$C$33 -> 150
D42: =SUM(D36:D41) -> 1500

Sheet Tabela_auxiliar
B3: CHAVE-COMPOSTA | C3: PERFIL | D3: TIPO DE FII | E3: %
B4: =C4&"-"&D4 -> Conservador-PAPEL | C4: Conservador | D4: PAPEL | E4: 0.3
B5: =C5&"-"&D5 -> Conservador-TIJOLO | C5: Conservador | D5: TIJOLO | E5: 0.5
B6: =C6&"-"&D6 -> Conservador-HÍBRIDOS | C6: Conservador | D6: HÍBRIDOS | E6: 0.1
B7: =C7&"-"&D7 -> Conservador-FOFs | C7: Conservador | D7: FOFs | E7: 0.1
B8: =C8&"-"&D8 -> Conservador-DESENVOLVIMENTO | C8: Conservador | D8: DESENVOLVIMENTO | E8: 0
B9: =C9&"-"&D9 -> Conservador-HOTELARIAS | C9: Conservador | D9: HOTELARIAS | E9: 0
B10: =C10&"-"&D10 -> Moderado-PAPEL | C10: Moderado | D10: PAPEL | E10: 0.32
B11: =C11&"-"&D11 -> Moderado-TIJOLO | C11: Moderado | D11: TIJOLO | E11: 0.35
B12: =C12&"-"&D12 -> Moderado-HÍBRIDOS | C12: Moderado | D12: HÍBRIDOS | E12: 0.08
B13: =C13&"-"&D13 -> Moderado-FOFs | C13: Moderado | D13: FOFs | E13: 0.05
B14: =C14&"-"&D14 -> Moderado-DESENVOLVIMENTO | C14: Moderado | D14: DESENVOLVIMENTO | E14: 0.1
B15: =C15&"-"&D15 -> Moderado-HOTELARIAS | C15: Moderado | D15: HOTELARIAS | E15: 0.1
... B21: =C21&"-"&D21 -> Agressivo-HOTELARIAS | C21: Agressivo | D21: HOTELARIAS | E21: 0.1
